j2lint/__init__.py
j2lint/__main__.py
j2lint/cli.py
j2lint/logger.py
j2lint/utils.py
j2lint/linter/__init__.py
j2lint/linter/collection.py
j2lint/linter/error.py
j2lint/linter/rule.py
j2lint/linter/runner.py
j2lint/linter/indenter/__init__.py
j2lint/linter/indenter/node.py
j2lint/linter/indenter/statement.py
j2lint/rules/__init__.py
j2lint/rules/jinja_operator_has_spaces_rule.py
j2lint/rules/jinja_statement_delimiter_rule.py
j2lint/rules/jinja_statement_has_spaces_rule.py
j2lint/rules/jinja_template_indentation_rule.py
j2lint/rules/jinja_template_no_tabs_rule.py
j2lint/rules/jinja_template_single_statement_rule.py
j2lint/rules/jinja_template_syntax_error_rule.py
j2lint/rules/jinja_variable_has_space_rule.py
j2lint/rules/jinja_variable_name_case_rule.py
j2lint/rules/jinja_variable_name_format_rule.py
j2lint-1.2.0.dist-info/licenses/LICENSE
j2lint-1.2.0.dist-info/METADATA
j2lint-1.2.0.dist-info/WHEEL
j2lint-1.2.0.dist-info/entry_points.txt
j2lint-1.2.0.dist-info/top_level.txt
j2lint-1.2.0.dist-info/RECORD
