Metadata-Version: 2.4
Name: j2lint
Version: 1.2.0
Summary: Command-line utility that validates jinja2 syntax according to Arista's AVD style guide.
Author-email: Arista Ansible Team <ansible@arista.com>
License: MIT License
Project-URL: Homepage, https://github.com/aristanetworks/j2lint.git
Project-URL: Bug Tracker, https://github.com/aristanetworks/j2lint/issues
Keywords: j2lint,linter,jinja,lint
Classifier: License :: OSI Approved :: MIT License
Classifier: Operating System :: OS Independent
Classifier: Development Status :: 5 - Production/Stable
Classifier: Intended Audience :: Developers
Classifier: Programming Language :: Python
Classifier: Programming Language :: Python :: 3
Classifier: Programming Language :: Python :: 3.9
Classifier: Programming Language :: Python :: 3.10
Classifier: Programming Language :: Python :: 3.11
Classifier: Programming Language :: Python :: 3.12
Classifier: Programming Language :: Python :: 3.13
Classifier: Topic :: Software Development :: Libraries :: Python Modules
Classifier: Topic :: Software Development :: Testing
Requires-Python: >=3.9
License-File: LICENSE
Requires-Dist: jinja2>=3.0
Requires-Dist: rich<15,>=13.5.2
Provides-Extra: dev
Requires-Dist: pre-commit>=3.3.3; extra == "dev"
Requires-Dist: bumpver==2024.1130; extra == "dev"
Requires-Dist: tox<5.0.0,>=4.10.0; extra == "dev"
Provides-Extra: test
Requires-Dist: pytest>=7.4.0; extra == "test"
Requires-Dist: pytest-cov>=4.1.0; extra == "test"
Provides-Extra: lint
Requires-Dist: pylint>=3.0.0; extra == "lint"
Requires-Dist: ruff<0.12.0,>=0.11.0; extra == "lint"
Requires-Dist: codespell<2.5.0,>=2.2.6; extra == "lint"
Provides-Extra: type
Requires-Dist: mypy==1.15.0; extra == "type"
Dynamic: license-file
